exasol/driver/__init__.py
exasol/driver/websocket/__init__.py
exasol/driver/websocket/_connection.py
exasol/driver/websocket/_cursor.py
exasol/driver/websocket/_errors.py
exasol/driver/websocket/_protocols.py
exasol/driver/websocket/_types.py
exasol/driver/websocket/dbapi2.py
pyexasol/__init__.py
pyexasol/__main__.py
pyexasol/callback.py
pyexasol/connection.py
pyexasol/constant.py
pyexasol/db2/__init__.py
pyexasol/exceptions.py
pyexasol/ext.py
pyexasol/formatter.py
pyexasol/http_transport.py
pyexasol/local_config.py
pyexasol/logger.py
pyexasol/mapper.py
pyexasol/meta.py
pyexasol/py.typed
pyexasol/script_output.py
pyexasol/statement.py
pyexasol/version.py
pyexasol/warnings.py
pyexasol_utils/__init__.py
pyexasol_utils/bench.py
pyexasol_utils/bench_sql/prepare.sql
pyexasol_utils/bench_sql/t1_group_by.sql
pyexasol_utils/bench_sql/t2_local_join.sql
pyexasol_utils/bench_sql/t3_global_join.sql
pyexasol_utils/bench_sql/t4_sort.sql
pyexasol_utils/docker_util.py
pyexasol_utils/script_output.py
pyexasol-2.0.0.dist-info/LICENSE.txt
pyexasol-2.0.0.dist-info/METADATA
pyexasol-2.0.0.dist-info/WHEEL
pyexasol-2.0.0.dist-info/RECORD
