Metadata-Version: 2.3
Name: pyexasol
Version: 2.0.0
Summary: Exasol python driver with extra features
License: MIT
Keywords: exasol,sql,database,performance,websocket,import,export
Author: Vitaly Markov
Author-email: wild.desu@gmail.com
Requires-Python: >=3.10,<3.15
Classifier: Development Status :: 5 - Production/Stable
Classifier: Intended Audience :: Developers
Classifier: License :: OSI Approved :: MIT License
Classifier: Programming Language :: Python :: 3
Classifier: Programming Language :: Python :: 3.10
Classifier: Programming Language :: Python :: 3.11
Classifier: Programming Language :: Python :: 3.12
Classifier: Programming Language :: Python :: 3.13
Classifier: Topic :: Database
Provides-Extra: all
Provides-Extra: examples
Provides-Extra: orjson
Provides-Extra: pandas
Provides-Extra: polars
Provides-Extra: pyarrow
Provides-Extra: rapidjson
Provides-Extra: ujson
Requires-Dist: cryptography (>=45.0.7)
Requires-Dist: orjson (>=3.6,<4.0) ; extra == "all"
Requires-Dist: orjson (>=3.6,<4.0) ; extra == "orjson"
Requires-Dist: packaging (>=24.1.0,<26.0.0)
Requires-Dist: pandas (>=2.0.0,<3.0.0) ; extra == "all"
Requires-Dist: pandas (>=2.0.0,<3.0.0) ; extra == "pandas"
Requires-Dist: polars (>=1.10.0,<2.0.0) ; extra == "all"
Requires-Dist: polars (>=1.10.0,<2.0.0) ; extra == "polars"
Requires-Dist: pproxy ; extra == "all"
Requires-Dist: pproxy ; extra == "examples"
Requires-Dist: pyarrow (>=21.0.0) ; extra == "all"
Requires-Dist: pyarrow (>=21.0.0) ; extra == "pyarrow"
Requires-Dist: python-rapidjson (>=1.21.0,<2.0.0) ; extra == "all"
Requires-Dist: python-rapidjson (>=1.21.0,<2.0.0) ; extra == "rapidjson"
Requires-Dist: ujson (>=5.10.0,<6.0.0) ; extra == "all"
Requires-Dist: ujson (>=5.10.0,<6.0.0) ; extra == "ujson"
Requires-Dist: websocket-client (>=1.0.1,<1.9.0)
Project-URL: Changelog, https://github.com/exasol/pyexasol/blob/master/CHANGELOG.md
Project-URL: Documentation, https://github.com/exasol/pyexasol/
Project-URL: Homepage, https://www.exasol.com/
Project-URL: Issues, https://github.com/exasol/pyexasol/issues
Project-URL: Source, https://github.com/exasol/pyexasol
